LICENSE
MANIFEST.in
README.md
setup.py
CINvalidator/CINvalidator.py
CINvalidator/__init__.py
CINvalidator.egg-info/PKG-INFO
CINvalidator.egg-info/SOURCES.txt
CINvalidator.egg-info/dependency_links.txt
CINvalidator.egg-info/top_level.txt