Metadata-Version: 1.0
Name: CINvalidator
Version: 0.0.5
Summary: China Citizen Identification Number Validator
Home-page: https://github.com/imlonghao/CIN-validator
Author: imlonghao
Author-email: shield@fastmail.com
License: Apache License 2.0
Keywords: Validator,Citizen Identification Number
Platform: any
